giantbomb/__init__.py
giantbomb/dataclasses.py
giantbomb/giantbomb.py
giantbomb_redux-1.0.6.dist-info/LICENSE.txt
giantbomb_redux-1.0.6.dist-info/METADATA
giantbomb_redux-1.0.6.dist-info/WHEEL
giantbomb_redux-1.0.6.dist-info/top_level.txt
giantbomb_redux-1.0.6.dist-info/RECORD
