Metadata-Version: 2.1
Name: giantbomb-redux
Version: 1.0.6
Summary: A Python wrapper for the Giantbomb API.
Home-page: https://github.com/ganonmaster/GiantBomb-redux
Author: Hidde Jansen <hidde@hiddejansen.com>
Author-email: hidde@hiddejansen.com
License: MIT
Keywords: giantbomb api wrapper
Platform: UNKNOWN
Classifier: Environment :: Console
Classifier: Intended Audience :: Developers
Classifier: Operating System :: OS Independent
Classifier: Topic :: Software Development :: Libraries :: Python Modules
Classifier: License :: OSI Approved :: MIT License
Requires-Python: >=3.7
Requires-Dist: requests (>=2.22.0)
Requires-Dist: dacite (>=1.0.2)
